efficientllm/__init__.py
efficientllm/__main__.py
efficientllm/cli.py
efficientllm/core.py
efficientllm_toolkit-1.0.5.dist-info/METADATA
efficientllm_toolkit-1.0.5.dist-info/WHEEL
efficientllm_toolkit-1.0.5.dist-info/entry_points.txt
efficientllm_toolkit-1.0.5.dist-info/top_level.txt
efficientllm_toolkit-1.0.5.dist-info/RECORD
